{
    "title": "Icon",
    "classname": ".c-icon",
    "variations": [
        {
            "title": "Alert",
            "icon": "alert"
        },
        {
            "title": "Arrow Down",
            "icon": "arrow-down"
        },
        {
            "title": "Github",
            "icon": "github"
        },
        {
            "title": "Info",
            "icon": "info"
        },
        {
            "title": "Plus",
            "icon": "plus"
        },
        {
            "title": "Warning",
            "icon": "warning"
        },
        {
            "title": "X",
            "icon": "x"
        },
        {
            "title": "Facebook",
            "icon": "facebook"
        },
        {
            "title": "Instagram",
            "icon": "instagram"
        },
        {
            "title": "Twitter",
            "icon": "twitter"
        },
        {
            "title": "YouTube",
            "icon": "youtube"
        },
        {
            "title": "LinkedIn",
            "icon": "linkedin"
        },
        {
            "title": "Pinterest",
            "icon": "pinterest"
        }
    ]
}
